trans_hub/__init__.py
trans_hub/cache.py
trans_hub/config.py
trans_hub/coordinator.py
trans_hub/db/__init__.py
trans_hub/db/migrations/001_initial.sql
trans_hub/db/migrations/__init__.py
trans_hub/db/schema_manager.py
trans_hub/engine_registry.py
trans_hub/engines/__init__.py
trans_hub/engines/base.py
trans_hub/engines/debug.py
trans_hub/engines/meta.py
trans_hub/engines/openai.py
trans_hub/engines/translators_engine.py
trans_hub/interfaces.py
trans_hub/logging_config.py
trans_hub/persistence.py
trans_hub/rate_limiter.py
trans_hub/types.py
trans_hub/utils.py
trans_hub-2.2.0.dist-info/LICENSE.md
trans_hub-2.2.0.dist-info/METADATA
trans_hub-2.2.0.dist-info/WHEEL
trans_hub-2.2.0.dist-info/RECORD
