Metadata-Version: 2.3
Name: trans-hub
Version: 2.2.0
Summary: 一个可嵌入的、带持久化存储的智能本地化（i18n）后端引擎。
License: MIT
Author: Saken
Author-email: saken.w@gmail.com
Requires-Python: >=3.9,<3.14
Classifier: Development Status :: 5 - Production/Stable
Classifier: Intended Audience :: Developers
Classifier: License :: OSI Approved :: MIT License
Classifier: Operating System :: OS Independent
Classifier: Programming Language :: Python :: 3
Classifier: Programming Language :: Python :: 3.9
Classifier: Programming Language :: Python :: 3.10
Classifier: Programming Language :: Python :: 3.11
Classifier: Programming Language :: Python :: 3.12
Classifier: Programming Language :: Python :: 3.13
Provides-Extra: openai
Provides-Extra: translators
Requires-Dist: aiosqlite (>=0.20.0,<0.21.0)
Requires-Dist: cachetools (>=5.3.3,<6.0.0)
Requires-Dist: openai (>=1.37.0,<2.0.0) ; extra == "openai"
Requires-Dist: pydantic (>=2.0,<3.0)
Requires-Dist: pydantic-settings[dotenv] (>=2.3.4,<3.0.0)
Requires-Dist: structlog (>=23.0,<24.0)
Requires-Dist: translators (>=6.0.1,<7.0.0) ; extra == "translators"
Project-URL: Documentation, https://github.com/SakenW/trans-hub/blob/main/docs/INDEX.md
Project-URL: Homepage, https://github.com/SakenW/trans-hub
Project-URL: Repository, https://github.com/SakenW/trans-hub
